jira_time/__init__.py
jira_time/worklogger.py
jira_time-1.0.0.dist-info/METADATA
jira_time-1.0.0.dist-info/WHEEL
jira_time-1.0.0.dist-info/entry_points.txt
jira_time-1.0.0.dist-info/licenses/LICENSE
jira_time-1.0.0.dist-info/RECORD
