Metadata-Version: 2.4
Name: jira-time
Version: 1.0.0
Summary: A CLI utility to track how much time you spent on JIRA tickets
License-Expression: MIT
License-File: LICENSE
Author: Jonathan Hoffman
Author-email: jonathan.hoffman91@gmail.com
Requires-Python: >=3.10
Classifier: Programming Language :: Python :: 3
Classifier: Programming Language :: Python :: 3.10
Classifier: Programming Language :: Python :: 3.11
Classifier: Programming Language :: Python :: 3.12
Classifier: Programming Language :: Python :: 3.13
Classifier: Programming Language :: Python :: 3.14
Requires-Dist: halo (>=0.0.31,<0.0.32)
Requires-Dist: jira (>=3.8.0,<4.0.0)
Requires-Dist: questionary (>=2.1.0,<3.0.0)
Project-URL: Bug Tracker, https://github.com/jonnyhoff/jira-time/issues
Project-URL: Documentation, https://github.com/jonnyhoff/jira-time/blob/main/README.md
Project-URL: Repository, https://github.com/jonnyhoff/jira-time
